README.rst
setup.py
buptelecmon/__init__.py
buptelecmon/animateprogress.py
buptelecmon/configurationmanager.py
buptelecmon/electricitymonitor.py
buptelecmon/exceptions.py
buptelecmon/logger.py
buptelecmon/main.py
buptelecmon/version.py
buptelecmon.egg-info/PKG-INFO
buptelecmon.egg-info/SOURCES.txt
buptelecmon.egg-info/dependency_links.txt
buptelecmon.egg-info/entry_points.txt
buptelecmon.egg-info/requires.txt
buptelecmon.egg-info/top_level.txt
buptelecmon.egg-info/zip-safe