Metadata-Version: 1.1
Name: buptelecmon
Version: 1.1.0
Summary: A program for checking electricity charge.
Home-page: https://github.com/jerrymakesjelly/electricity-monitor
Author: jerrymakesjelly
Author-email: ganzhaoyu037@gmail.com
License: MIT
Keywords: python bupt electricity
Platform: UNKNOWN
Classifier: Development Status :: 5 - Production/Stable
Classifier: Environment :: Console
Classifier: License :: OSI Approved :: MIT License
Classifier: Programming Language :: Python :: 3 :: Only
Classifier: Topic :: Utilities
